ndstorage/__init__.py
ndstorage/_superclass.py
ndstorage/_version.py
ndstorage/file_io.py
ndstorage/ndram_dataset.py
ndstorage/ndstorage_base.py
ndstorage/ndtiff_dataset.py
ndstorage/ndtiff_file.py
ndstorage/ndtiff_index.py
ndstorage/ndtiff_pyramid_dataset.py
ndstorage/old_format_version_readers/__init__.py
ndstorage/old_format_version_readers/nd_tiff_v2.py
ndstorage/old_format_version_readers/ndtiff_v1.py
ndstorage/test/__init__.py
ndstorage/test/conftest.py
ndstorage/test/data_loading_test.py
ndstorage/test/test_custom_io.py
ndstorage/test/write_speed_test.py
ndstorage/test/writing_test.py
ndstorage-0.1.18.dist-info/LICENSE
ndstorage-0.1.18.dist-info/WHEEL
ndstorage-0.1.18.dist-info/METADATA
ndstorage-0.1.18.dist-info/RECORD
